zteradb/__init__.py
zteradb/zteradb_client_async.py
zteradb/zteradb_config.py
zteradb/zteradb_exception.py
zteradb/zteradb_filter_functions.py
zteradb/helper/__init__.py
zteradb/helper/zteradb_common.py
zteradb/lib/__init__.py
zteradb/lib/zteradb_auth.py
zteradb/lib/zteradb_connection.py
zteradb/lib/zteradb_connection_protocol.py
zteradb/lib/zteradb_data_manager.py
zteradb/lib/zteradb_filter_condition_functions.py
zteradb/lib/zteradb_filter_conditions.py
zteradb/lib/zteradb_filter_types.py
zteradb/lib/zteradb_protocol.py
zteradb/lib/zteradb_query.py
zteradb/lib/zteradb_query_type.py
zteradb/lib/zteradb_request_types.py
zteradb-1.0.3.dist-info/LICENCE
zteradb-1.0.3.dist-info/METADATA
zteradb-1.0.3.dist-info/WHEEL
zteradb-1.0.3.dist-info/top_level.txt
zteradb-1.0.3.dist-info/RECORD
