Metadata-Version: 2.1
Name: zteradb
Version: 1.0.3
Summary: ZTeraDB is a Python client library designed to simplify interactions with ZTeraDB.It provides a set of classes and tools that enable seamless integration, allowing developers to easily manage database operations and queries.
Home-page: https://github.com/zteradb/zteradb-python.git
Author: ZTeraDB
Author-email: iashokin@gmail.com
License: ZTeraDB
Platform: UNKNOWN
Classifier: Programming Language :: Python :: 3
Classifier: Operating System :: OS Independent
Requires-Python: >=3.7
License-File: LICENCE
